feature_engineering/__init__.py
feature_engineering/feature_generator.py
feature_engineering/test.py
feature_engineering/test_feature_engineering.py
flows/__init__.py
flows/example.yaml
flows/flow_0.json
flows/flow_1.json
flows/flow_2.json
flows/flow_3.json
flows/flow_4.json
flows/flow_5.json
flows/flow_instructions.py
flows/flow_instructions_database.yaml
flows/flows.py
flows/utils.py
flows/yaml_reader.py
prediction/__init__.py
prediction/model_predictor.py
preprocessing/__init__.py
preprocessing/data_clean.py
preprocessing/data_explorer.py
preprocessing/data_science_help_functions.py
preprocessing/data_transformer.py
preprocessing/data_type_detector.py
preprocessing/json_preprocessor.py
preprocessing/test_data_science_help_functions.py
preprocessing/test_loading_data.py
preprocessing/test_outliers.py
preprocessing/test_preprocessing.py
preprocessing/utils.py
training/__init__.py
training/classification_model_evaluator.py
training/gridsearch_train.py
training/model_evaluator.py
training/optimizer.py
training/regression_model_evaluator.py
training/test_split.py
training/test_training.py
training/test_validator.py
training/test_xgboost.py
training/training.py
training/utils.py
training/validator.py
training/xgboost_train.py
visualization/__init__.py
visualization/visualization.py
ML_Navigator-0.0.32.dist-info/LICENSE
ML_Navigator-0.0.32.dist-info/METADATA
ML_Navigator-0.0.32.dist-info/WHEEL
ML_Navigator-0.0.32.dist-info/top_level.txt
ML_Navigator-0.0.32.dist-info/RECORD
